CHANGELOG
COPYRIGHT
INSTALL
LICENSE
MANIFEST.in
README
TODO
account_retencion_ar.xml
account_voucher_ar.xml
setup.py
tryton.cfg
./__init__.py
./account_retencion_ar.py
./account_retencion_ar.xml
./account_voucher_ar.py
./account_voucher_ar.xml
./tryton.cfg
./locale/es_AR.po
./view/account_retencion_efectuada_form.xml
./view/account_retencion_efectuada_tree.xml
./view/account_retencion_form.xml
./view/account_retencion_soportada_form.xml
./view/account_retencion_soportada_tree.xml
./view/account_retencion_tree.xml
./view/retenciones_efectuadas_tree.xml
./view/retenciones_soportadas_tree.xml
./view/voucher_retencion_form.xml
locale/es_AR.po
trytonar_account_retencion_ar.egg-info/PKG-INFO
trytonar_account_retencion_ar.egg-info/SOURCES.txt
trytonar_account_retencion_ar.egg-info/dependency_links.txt
trytonar_account_retencion_ar.egg-info/entry_points.txt
trytonar_account_retencion_ar.egg-info/not-zip-safe
trytonar_account_retencion_ar.egg-info/requires.txt
trytonar_account_retencion_ar.egg-info/top_level.txt
view/account_retencion_efectuada_form.xml
view/account_retencion_efectuada_tree.xml
view/account_retencion_form.xml
view/account_retencion_soportada_form.xml
view/account_retencion_soportada_tree.xml
view/account_retencion_tree.xml
view/retenciones_efectuadas_tree.xml
view/retenciones_soportadas_tree.xml
view/voucher_retencion_form.xml